{
	"name": "DL_PQT_VBAP",
	"properties": {
		"linkedServiceName": {
			"referenceName": "edw-prd-WorkspaceDefaultStorage",
			"type": "LinkedServiceReference"
		},
		"folder": {
			"name": "DataLake_Levis/Transacciones/04 Consumption"
		},
		"annotations": [],
		"type": "Parquet",
		"typeProperties": {
			"location": {
				"type": "AzureBlobFSLocation",
				"fileName": "VBAP.parquet",
				"folderPath": "3_consumption_zone/Datalake/DL_DATOS_MAESTROS/VBAP",
				"fileSystem": "edwlakeprd"
			},
			"compressionCodec": "snappy"
		},
		"schema": []
	},
	"type": "Microsoft.Synapse/workspaces/datasets"
}